giu/__init__.py
giu/cli.py
giu/config.py
giu/livedns.py
giu/resolver.py
giu-0.3.5.dist-info/entry_points.txt
giu-0.3.5.dist-info/LICENSE
giu-0.3.5.dist-info/WHEEL
giu-0.3.5.dist-info/METADATA
giu-0.3.5.dist-info/RECORD
