Metadata-Version: 2.1
Name: giu
Version: 0.3.5
Summary: Gandi LiveDNS Updater - Command line tool to keep your dynamic ip up to date
Home-page: https://github.com/yriveiro/giu
License: MIT
Keywords: Gandi,LiveDNS,Dynamic IP,dns
Author: Yago Riveiro
Author-email: yago.riveiro@gmail.com
Maintainer: Yago Riveiro
Maintainer-email: yago.riveiro@gmail.com
Requires-Python: >=3.8,<4.0
Classifier: Development Status :: 4 - Beta
Classifier: Environment :: Console
Classifier: Framework :: tox
Classifier: License :: OSI Approved :: MIT License
Classifier: Programming Language :: Python :: 3
Classifier: Programming Language :: Python :: 3.8
Classifier: Programming Language :: Python :: 3.9
Classifier: Programming Language :: Python :: 3.10
Classifier: Programming Language :: Python :: 3.11
Classifier: Programming Language :: Python :: 3.10
Classifier: Programming Language :: Python :: 3.11
Classifier: Programming Language :: Python :: 3.6
Classifier: Programming Language :: Python :: 3.7
Classifier: Programming Language :: Python :: 3.8
Classifier: Programming Language :: Python :: 3.9
Classifier: Programming Language :: Python :: Implementation :: CPython
Classifier: Topic :: Internet :: Name Service (DNS)
Requires-Dist: atoml (>=1.1.1,<2.0.0)
Requires-Dist: click (>=8.1.3,<9.0.0)
Requires-Dist: halo (>=0.0.31,<0.0.32)
Requires-Dist: requests (>=2.28.1,<3.0.0)
Project-URL: Repository, https://github.com/yriveiro/giu
